transmission_unlinked/__init__.py
transmission_unlinked/core.py
transmission_unlinked/main.py
transmission_unlinked-0.2.3.dist-info/licenses/LICENSE
transmission_unlinked-0.2.3.dist-info/METADATA
transmission_unlinked-0.2.3.dist-info/WHEEL
transmission_unlinked-0.2.3.dist-info/entry_points.txt
transmission_unlinked-0.2.3.dist-info/top_level.txt
transmission_unlinked-0.2.3.dist-info/RECORD
