Metadata-Version: 2.4
Name: transmission-unlinked
Version: 0.2.3
Summary: Helps you remove your transmission torrents which have no hardlinks
Author-email: Your Name <flying_sausages@protonmail.com>
Maintainer-email: Your Name <flying_sausages@protonmail.com>
License: MIT
Project-URL: Homepage, https://github.com/flying-sausages/transmission-unlinked
Project-URL: Repository, https://github.com/flying-sausages/transmission-unlinked
Project-URL: Issues, https://github.com/flying-sausages/transmission-unlinked/issues
Keywords: transmission,torrent,hardlinks,cleanup,bittorrent
Classifier: Intended Audience :: End Users/Desktop
Classifier: Intended Audience :: System Administrators
Classifier: License :: OSI Approved :: MIT License
Classifier: Operating System :: OS Independent
Classifier: Programming Language :: Python :: 3
Classifier: Programming Language :: Python :: 3.10
Classifier: Programming Language :: Python :: 3.11
Classifier: Programming Language :: Python :: 3.12
Classifier: Programming Language :: Python :: 3.13
Classifier: Topic :: Communications :: File Sharing
Classifier: Topic :: System :: Filesystems
Classifier: Topic :: Utilities
Requires-Python: >=3.10
License-File: LICENSE
Requires-Dist: transmission-rpc>=7.0.11
Dynamic: license-file
